Metadata-Version: 2.1
Name: libpythonpro-leandro
Version: 1.0
Summary: Módulo para exemplificar construção de projetos Python no curso PyTools
Home-page: https://github.com/LeandroBP/libpythonpro
Author: Leandro Batista Pereira
Author-email: leandrobatistapereira98@gmail.com
License: GNU AFFERO GENERAL PUBLIC LICENSE
Platform: UNKNOWN
Classifier: Development Status :: 2 - Pre-Alpha
Classifier: Environment :: Console
Classifier: Intended Audience :: Developers
Classifier: License :: OSI Approved :: GNU Affero General Public License v3 or later (AGPLv3+)
Classifier: Operating System :: OS Independent
Classifier: Programming Language :: Python :: 3.7
Classifier: Framework :: Pytest
